README.md
enigma_download.sh
setup.cfg
setup.py
nifti_snapshot/__init__.py
nifti_snapshot/nifti_snapshot.py
nifti_snapshot/nifti_snapshot_utils.py
nifti_snapshot.egg-info/PKG-INFO
nifti_snapshot.egg-info/SOURCES.txt
nifti_snapshot.egg-info/dependency_links.txt
nifti_snapshot.egg-info/requires.txt
nifti_snapshot.egg-info/top_level.txt
scripts/nifti_snapshot