Metadata-Version: 2.1
Name: nifti-snapshot
Version: 0.1.13
Summary: First release to test pypi
Home-page: https://github.com/pnlbwh/nifti-snapshot
Download-URL: https://github.com/pnlbwh/nifti-snapshot/archive/refs/tags/v0.1.12.zip
Author: kcho
Author-email: kevincho@bwh.harvard.edu
License: UNKNOWN
Keywords: nifti,snapshot
Platform: UNKNOWN
Classifier: Programming Language :: Python :: 3
Classifier: License :: OSI Approved :: MIT License
Requires-Python: >=3.7
